odoo/addons/mrp_production_picking_type_from_route/README.rst
odoo/addons/mrp_production_picking_type_from_route/__init__.py
odoo/addons/mrp_production_picking_type_from_route/__manifest__.py
odoo/addons/mrp_production_picking_type_from_route/i18n/it.po
odoo/addons/mrp_production_picking_type_from_route/i18n/mrp_production_picking_type_from_route.pot
odoo/addons/mrp_production_picking_type_from_route/models/__init__.py
odoo/addons/mrp_production_picking_type_from_route/models/mrp_production.py
odoo/addons/mrp_production_picking_type_from_route/readme/CONTRIBUTORS.rst
odoo/addons/mrp_production_picking_type_from_route/readme/DESCRIPTION.rst
odoo/addons/mrp_production_picking_type_from_route/readme/USAGE.rst
odoo/addons/mrp_production_picking_type_from_route/static/description/icon.png
odoo/addons/mrp_production_picking_type_from_route/static/description/index.html
odoo/addons/mrp_production_picking_type_from_route/tests/__init__.py
odoo/addons/mrp_production_picking_type_from_route/tests/test_mrp_production_picking_type_from_route.py
odoo14_addon_mrp_production_picking_type_from_route-14.0.1.0.1.dev6.dist-info/METADATA
odoo14_addon_mrp_production_picking_type_from_route-14.0.1.0.1.dev6.dist-info/WHEEL
odoo14_addon_mrp_production_picking_type_from_route-14.0.1.0.1.dev6.dist-info/top_level.txt
odoo14_addon_mrp_production_picking_type_from_route-14.0.1.0.1.dev6.dist-info/RECORD
